quora_profile_search/__init__.py
quora_profile_search/main.py
quora_profile_search-1.0.4.dist-info/License.txt
quora_profile_search-1.0.4.dist-info/METADATA
quora_profile_search-1.0.4.dist-info/WHEEL
quora_profile_search-1.0.4.dist-info/top_level.txt
quora_profile_search-1.0.4.dist-info/RECORD
