Metadata-Version: 2.1
Name: quora-profile-search
Version: 1.0.4
Summary: A basic profile search bot for Quora
Home-page: UNKNOWN
Author: Abdessamad BAAHMED
Author-email: baahmedabdessamad@outlook.com
License: UNKNOWN
Keywords: python,reddit,profile,search
Platform: UNKNOWN
Classifier: Development Status :: 1 - Planning
Classifier: Intended Audience :: Developers
Classifier: Programming Language :: Python :: 3
Classifier: Operating System :: Unix
Classifier: Operating System :: MacOS :: MacOS X
Classifier: Operating System :: Microsoft :: Windows
Requires-Dist: async-generator
Requires-Dist: attrs
Requires-Dist: beautifulsoup4
Requires-Dist: bs4
Requires-Dist: certifi
Requires-Dist: cffi
Requires-Dist: cryptography
Requires-Dist: h11
Requires-Dist: idna
Requires-Dist: outcome
Requires-Dist: pycparser
Requires-Dist: pyOpenSSL
Requires-Dist: PySocks
Requires-Dist: selenium
Requires-Dist: sniffio
Requires-Dist: sortedcontainers
Requires-Dist: soupsieve
Requires-Dist: trio
Requires-Dist: trio-websocket
Requires-Dist: urllib3
Requires-Dist: wsproto
